code_builder/__init__.py
code_builder/ml_data_class_builder.py
code_builder/name_conventions.py
code_builder/streamlit_builder.py
data_analytics/__init__.py
data_analytics/exploratory_data_analysis.py
data_analytics/exploratory_data_analysis_reports.py
data_analytics/github.py
data_analytics/graphs.py
data_analytics/machine_learning.py
data_analytics/zip_file.py
markcrowe/__init__.py
markcrowe/support.py
population_planning/__init__.py
population_planning/dataframe_labels.py
population_planning/project_manager.py
markcrowe-0.1.1.dist-info/METADATA
markcrowe-0.1.1.dist-info/WHEEL
markcrowe-0.1.1.dist-info/license
markcrowe-0.1.1.dist-info/top_level.txt
markcrowe-0.1.1.dist-info/RECORD
