Metadata-Version: 2.1
Name: markcrowe
Version: 0.1.1
Summary: Data analytic functions for data projects.
Home-page: https://github.com/marcocrowe/markcrowe.pypi/
Author: Mark Crowe
Author-email: 66536097+marcocrowe@users.noreply.github.com
Project-URL: Bug Tracker, https://github.com/marcocrowe/markcrowe.pypi/issues
Classifier: Programming Language :: Python :: 3
Classifier: Operating System :: OS Independent
Requires-Python: >=3.6
License-File: license
